{
  "dept_code": "305",
  "dept_name": "企業管理學系",
  "dept_name_full": "",
  "college": "商學院",
  "entry_year": 112,
  "gopnum": "",
  "key": "305",
  "source_url": "https://moltke.nccu.edu.tw/tsreqsub_SSO/reqsub.tsreqsub?gdetpe=1&yy=112&gopnum=&depnum=305",
  "total_courses": 17,
  "courses": [
    {
      "name": "經濟學",
      "type": "必修",
      "credits": 6,
      "semesters": 2,
      "schedule": {
        "y1s1": true,
        "y1s2": true,
        "y2s1": false,
        "y2s2": false,
        "y3s1": false,
        "y3s2": false,
        "y4s1": false,
        "y4s2": false
      },
      "recognition": "不限",
      "course_code_required": "000219",
      "double_major_recognition": "不限",
      "double_major_course_code": "000219",
      "note": "無"
    },
    {
      "name": "初級會計學（一）",
      "type": "必修",
      "credits": 3,
      "semesters": 1,
      "schedule": {
        "y1s1": true,
        "y1s2": false,
        "y2s1": false,
        "y2s2": false,
        "y3s1": false,
        "y3s2": false,
        "y4s1": false,
        "y4s2": false
      },
      "recognition": "不限",
      "course_code_required": "000314",
      "double_major_recognition": "不限",
      "double_major_course_code": "000314",
      "note": "無"
    },
    {
      "name": "微積分",
      "type": "必修",
      "credits": 3,
      "semesters": 1,
      "schedule": {
        "y1s1": true,
        "y1s2": false,
        "y2s1": false,
        "y2s2": false,
        "y3s1": false,
        "y3s2": false,
        "y4s1": false,
        "y4s2": false
      },
      "recognition": "不限",
      "course_code_required": "000712",
      "double_major_recognition": "不限",
      "double_major_course_code": "000712",
      "note": "無"
    },
    {
      "name": "管理學",
      "type": "必修",
      "credits": 3,
      "semesters": 1,
      "schedule": {
        "y1s1": true,
        "y1s2": false,
        "y2s1": false,
        "y2s2": false,
        "y3s1": false,
        "y3s2": false,
        "y4s1": false,
        "y4s2": false
      },
      "recognition": "不限",
      "course_code_required": "000348",
      "double_major_recognition": "不限",
      "double_major_course_code": "000348",
      "note": "無"
    },
    {
      "name": "初級會計學（二）",
      "type": "必修",
      "credits": 3,
      "semesters": 1,
      "schedule": {
        "y1s1": true,
        "y1s2": false,
        "y2s1": false,
        "y2s2": false,
        "y3s1": false,
        "y3s2": false,
        "y4s1": false,
        "y4s2": false
      },
      "recognition": "不限",
      "course_code_required": "000318",
      "double_major_recognition": "不限",
      "double_major_course_code": "000318",
      "note": "先修：初級會計學(一)"
    },
    {
      "name": "管理科學",
      "type": "必修",
      "credits": 3,
      "semesters": 1,
      "schedule": {
        "y1s1": true,
        "y1s2": false,
        "y2s1": false,
        "y2s2": false,
        "y3s1": false,
        "y3s2": false,
        "y4s1": false,
        "y4s2": false
      },
      "recognition": "需為本系開課",
      "course_code_required": "無",
      "double_major_recognition": "需為本系開課",
      "double_major_course_code": "無",
      "note": "先修：管理學"
    },
    {
      "name": "商事法",
      "type": "必修",
      "credits": 2,
      "semesters": 1,
      "schedule": {
        "y1s1": true,
        "y1s2": false,
        "y2s1": false,
        "y2s2": false,
        "y3s1": false,
        "y3s2": false,
        "y4s1": false,
        "y4s2": false
      },
      "recognition": "不限",
      "course_code_required": "000604",
      "double_major_recognition": "不限",
      "double_major_course_code": "000604",
      "note": "無"
    },
    {
      "name": "統計學（一）",
      "type": "必修",
      "credits": 3,
      "semesters": 1,
      "schedule": {
        "y1s1": true,
        "y1s2": false,
        "y2s1": false,
        "y2s2": false,
        "y3s1": false,
        "y3s2": false,
        "y4s1": false,
        "y4s2": false
      },
      "recognition": "需為本院開課",
      "course_code_required": "無",
      "double_major_recognition": "需為本院開課",
      "double_major_course_code": "無",
      "note": "無"
    },
    {
      "name": "組織行為",
      "type": "必修",
      "credits": 3,
      "semesters": 1,
      "schedule": {
        "y1s1": true,
        "y1s2": false,
        "y2s1": false,
        "y2s2": false,
        "y3s1": false,
        "y3s2": false,
        "y4s1": false,
        "y4s2": false
      },
      "recognition": "需為本系開課",
      "course_code_required": "無",
      "double_major_recognition": "需為本系開課",
      "double_major_course_code": "無",
      "note": "先修：管理學"
    },
    {
      "name": "人力資源管理",
      "type": "必修",
      "credits": 3,
      "semesters": 1,
      "schedule": {
        "y1s1": true,
        "y1s2": false,
        "y2s1": false,
        "y2s2": false,
        "y3s1": false,
        "y3s2": false,
        "y4s1": false,
        "y4s2": false
      },
      "recognition": "需為本系開課",
      "course_code_required": "無",
      "double_major_recognition": "需為本系開課",
      "double_major_course_code": "無",
      "note": "先修：管理學與組織行為"
    },
    {
      "name": "行銷管理",
      "type": "必修",
      "credits": 3,
      "semesters": 1,
      "schedule": {
        "y1s1": true,
        "y1s2": false,
        "y2s1": false,
        "y2s2": false,
        "y3s1": false,
        "y3s2": false,
        "y4s1": false,
        "y4s2": false
      },
      "recognition": "不限",
      "course_code_required": "000350",
      "double_major_recognition": "不限",
      "double_major_course_code": "000350",
      "note": "先修：管理學與經濟學"
    },
    {
      "name": "財務管理",
      "type": "必修",
      "credits": 3,
      "semesters": 1,
      "schedule": {
        "y1s1": true,
        "y1s2": false,
        "y2s1": false,
        "y2s2": false,
        "y3s1": false,
        "y3s2": false,
        "y4s1": false,
        "y4s2": false
      },
      "recognition": "不限",
      "course_code_required": "000347",
      "double_major_recognition": "不限",
      "double_major_course_code": "000347",
      "note": "先修：經濟學與初級會計學（一）（二）；二上或二下修習。"
    },
    {
      "name": "統計學（二）",
      "type": "必修",
      "credits": 3,
      "semesters": 1,
      "schedule": {
        "y1s1": true,
        "y1s2": false,
        "y2s1": false,
        "y2s2": false,
        "y3s1": false,
        "y3s2": false,
        "y4s1": false,
        "y4s2": false
      },
      "recognition": "需為本院開課",
      "course_code_required": "無",
      "double_major_recognition": "需為本院開課",
      "double_major_course_code": "無",
      "note": "無"
    },
    {
      "name": "資訊管理",
      "type": "必修",
      "credits": 3,
      "semesters": 1,
      "schedule": {
        "y1s1": true,
        "y1s2": false,
        "y2s1": false,
        "y2s2": false,
        "y3s1": false,
        "y3s2": false,
        "y4s1": false,
        "y4s2": false
      },
      "recognition": "不限",
      "course_code_required": "無",
      "double_major_recognition": "不限",
      "double_major_course_code": "無",
      "note": "三上或三下修習"
    },
    {
      "name": "營運與供應鏈管理",
      "type": "必修",
      "credits": 3,
      "semesters": 1,
      "schedule": {
        "y1s1": true,
        "y1s2": false,
        "y2s1": false,
        "y2s2": false,
        "y3s1": false,
        "y3s2": false,
        "y4s1": false,
        "y4s2": false
      },
      "recognition": "需為本系開課",
      "course_code_required": "無",
      "double_major_recognition": "需為本院開課",
      "double_major_course_code": "無",
      "note": "無"
    },
    {
      "name": "企業倫理與社會責任",
      "type": "必修",
      "credits": 1,
      "semesters": 1,
      "schedule": {
        "y1s1": true,
        "y1s2": false,
        "y2s1": false,
        "y2s2": false,
        "y3s1": false,
        "y3s2": false,
        "y4s1": false,
        "y4s2": false
      },
      "recognition": "需為本院開課",
      "course_code_required": "無",
      "double_major_recognition": "需為本院開課",
      "double_major_course_code": "無",
      "note": "大三或大四修習"
    },
    {
      "name": "策略管理",
      "type": "必修",
      "credits": 3,
      "semesters": 1,
      "schedule": {
        "y1s1": true,
        "y1s2": false,
        "y2s1": false,
        "y2s2": false,
        "y3s1": false,
        "y3s2": false,
        "y4s1": false,
        "y4s2": false
      },
      "recognition": "需為本系開課",
      "course_code_required": "無",
      "double_major_recognition": "需為本系開課",
      "double_major_course_code": "無",
      "note": "先修：營運與供應鏈管理、行銷管理、人力資源管理、資訊管理及財務管理等五管；四上或四下修習"
    }
  ]
}